[
  {
    "name":"Akismet",
    "compat":"Checked",
    "class":"compatible"
  },
  
  {
    "name":"All In One SEO Pack",
    "compat":"Checked",
    "class":"compatible"
  },
  
  {
    "name":"Any Mobile Theme Switcher",
    "compat":"Checked",
    "class":"compatible"
  },
  
  {
    "name":"BAW Manual Related Posts",
    "compat":"Checked",
    "class":"compatible"
  },

  {
    "name":"Better Delete Revision",
    "compat":"No",
    "reason":"DELETE with JOIN/etc",
    "class":"incompatible"
  },

  {
    "name":"Better Related Posts",
    "compat":"No",
    "reason":"FULLTEXT index",
    "class":"incompatible"
  },

  {
    "name":"Breadcrumb NavXT",
    "compat":"Checked",
    "class":"compatible"
  },
  
  {
    "name":"Broken Link Checker",
    "compat":"Checked",
    "class":"compatible"
  },
  
  {
    "name":"Browser Shots",
    "compat":"Checked",
    "class":"compatible"
  },
  
  {
    "name":"Camera slideshow",
    "compat":"Needs Patch",
    "patch_url":"http://dogwood.skr.jp/wordpress/plugins/",
    "reason":"MySQL function",
    "class":"workaround"
  },
  
  {
    "name":"Category Order and Taxonomy Terms Order",
    "compat":"Checked",
    "class":"compatible"
  },
  
  {
    "name":"Contact Form 7",
    "compat":"Checked",
    "class":"compatible"
  },
  
  {
    "name":"Contact Form 7 reCAPTCHA extension",
    "compat":"Checked",
    "class":"compatible"
  },
  
  {
    "name":"Crayon Syntax Highlighter",
    "compat":"Checked",
    "class":"compatible"
  },
  
  {
    "name":"DB Cache Reloaded Fix",
    "compat":"Probably No",
    "reason":"db.php conflict",
    "class":"probable"
  },

  {
    "name":"Debug Bar",
    "compat":"Checked",
    "class":"compatible"
  },
  
  {
    "name":"Debug Bar Console",
    "compat":"Checked",
    "class":"compatible"
  },
  
  {
    "name":"Debug Bar Extender",
    "compat":"Checked",
    "class":"compatible"
  },
  
  {
    "name":"Dynamic To Top",
    "compat":"Checked",
    "class":"compatible"
  },
  
  {
    "name":"FeedWordPress",
    "compat":"Needs patch",
    "patch_url":"http://dogwood.skr.jp/wordpress/plugins/",
    "reason":"MySQL specific function",
    "class":"workaround"
  },
  
  {
    "name":"Google Analyticator",
    "compat":"Checked",
    "class":"compatible"
  },
  
  {
    "name":"Google Analytics Popular Posts",
    "compat":"Checked",
    "class":"compatible"
  },
  
  {
    "name":"Google XML Sitemaps",
    "compat":"Needs Patch",
    "patch_url":"http://dogwood.skr.jp/wordpress/plugins/",
    "reason":"MySQL function",
    "class":"workaround"
  },
  
  {
    "name":"Hello Dolly",
    "compat":"Checked",
    "class":"compatible"
  },
  
  {
    "name":"HyperDB",
    "compat":"Probably No",
    "reason":"db.php conflict",
    "class":"probable"
  },
  
  {
    "name":"Jetpack by WordPress.com",
    "compat":"Checked",
    "class":"compatible"
  },
  
  {
    "name":"Ktai Style",
    "compat":"Checked",
    "class":"compatible"
  },
  
  {
    "name":"Limit Login Attempts",
    "compat":"Checked",
    "class":"compatible"
  },
  
  {
  	"name":"Mathjax Latex",
  	"compat":"Checked",
  	"class":"compatible"
  },
  
  {
  	"name":"MP6",
  	"compat":"Checked",
  	"class":"compatible"
  },
  
  {
    "name":"NewStatPress",
    "compat":"Needs Patch",
    "patch_url":"http://dogwood.skr.jp/wordpress/plugins/",
    "reason":"MySQL specific data",
    "class":"workaround"
  },
	
	{
		"name":"NextGEN Gallery",
		"compat":"Needs patch",
		"patch_url":"http://dogwood.skr.jp/wordpress/plugins/",
		"reason":"MySQL specific function",
		"class":"workaround"
	},
  
  {
    "name":"Optimize Database after Deleting Revisions",
    "compat":"Probably No",
    "reason":"MySQL function/MySQL specific table",
    "class":"workaround"
  },
  
  {
    "name":"Polylang",
    "compat":"Checked",
    "class":"compatible"
  },
  
	{
		"name":"Redirection",
		"compat":"Checked",
		"class":"compatible"
	},
	
  {
    "name":"Related Posts",
    "compat":"Checked",
    "class":"compatible"
  },
  
  {
    "name":"Revision Cleaner",
    "compat":"Checked",
    "class":"compatible"
  },
  
  {
    "name":"Search Everything",
    "compat":"Checked",
    "class":"compatible"
  },
  
  {
    "name":"Search Meter",
    "compat":"Checked",
    "class":"compatible"
  },
  
  {
    "name":"SQLite Integration",
    "compat":"Checked",
    "class":"compatible"
  },
  
  {
    "name":"Synchi",
    "compat":"Checked",
    "class":"compatible"
  },
  
  {
    "name":"Theme-Check",
    "compat":"Checked",
    "class":"compatible"
  },
  
  {
    "name":"Wordfence Security",
    "compat":"Checked",
    "class":"compatible"
  },
  
  {
    "name":"WordPress Beta Tester",
    "compat":"Checked",
    "class":"compatible"
  },
  
	{
		"name":"WordPress Importer",
		"compat":"Checked",
		"class":"compatible"
	},
	
  {
    "name":"Wordpress Popular Posts",
    "compat":"Needs Patch",
		"patch_url":"http://dogwood.skr.jp/wordpress/plugins/",
		"reason":"MySQL specific query",
    "class":"workaround"
  },
  
  {
    "name":"WordPress Related Posts",
    "compat":"Checked",
    "class":"compatible"
  },
  
  {
    "name":"WP Emmet",
    "compat":"Checked",
    "class":"compatible"
  },
  
  {
    "name":"WP Multibyte Patch",
    "compat":"Checked",
    "class":"compatible"
  },
  
  {
    "name":"WP-PageNavi",
    "compat":"Checked",
    "class":"compatible"
  },
  
  {
    "name":"WP-PostRatings",
    "compat":"Checked",
    "class":"compatible"
  },

	{
		"name":"WP-PostViews",
		"compat":"Checked",
		"class":"compatible"
	},
	
  {
    "name":"WP-reCAPTCHA",
    "compat":"Checked",
    "class":"compatible"
  },
  
  {
    "name":"WP Social Bookmarking Light",
    "compat":"Checked",
    "class":"compatible"
  },
  
  {
    "name":"WP Super Cache",
    "compat":"Checked",
    "class":"compatible"
  },
  
  {
    "name":"WP Video Lightbox",
    "compat":"Checked",
    "class":"compatible"
  },
  
  {
    "name":"Wysija Newsletters",
    "compat":"Needs Patch",
    "patch_url":"http://dogwood.skr.jp/wordpress/plugins/",
    "reason":"MySQL function/table name",
    "class":"workaround"
  },
  
  {
    "name":"W3 Total Cache",
    "compat":"Probably No",
    "reason":"db.php conflict",
    "class":"probable"
  },
  
	{
		"name":"Yet Another Related Posts Plugin",
  	"compat":"No",
  	"reason":"FULLTEX index",
  	"class":"incompatible"
  }
]